setup.py
sm_mir/Indexer.py
sm_mir/Problem.py
sm_mir/__init__.py
sm_mir/use_example.py
sm_mir.egg-info/PKG-INFO
sm_mir.egg-info/SOURCES.txt
sm_mir.egg-info/dependency_links.txt
sm_mir.egg-info/not-zip-safe
sm_mir.egg-info/top_level.txt