Metadata-Version: 1.0
Name: sm-mir
Version: 0.1
Summary: Model Investigation Resource
Home-page: UNKNOWN
Author: UNKNOWN
Author-email: UNKNOWN
License: UNKNOWN
Platform: UNKNOWN
